MANIFEST.in
README.rst
buildout.cfg
setup.py
collective/__init__.py
collective.analyticspanel.egg-info/PKG-INFO
collective.analyticspanel.egg-info/SOURCES.txt
collective.analyticspanel.egg-info/dependency_links.txt
collective.analyticspanel.egg-info/entry_points.txt
collective.analyticspanel.egg-info/namespace_packages.txt
collective.analyticspanel.egg-info/not-zip-safe
collective.analyticspanel.egg-info/requires.txt
collective.analyticspanel.egg-info/top_level.txt
collective/analyticspanel/__init__.py
collective/analyticspanel/configure.zcml
collective/analyticspanel/interfaces.py
collective/analyticspanel/setuphandlers.py
collective/analyticspanel/testing.py
collective/analyticspanel/upgrades.zcml
collective/analyticspanel/vocabularies.py
collective/analyticspanel/Extensions/install.py
collective/analyticspanel/browser/__init__.py
collective/analyticspanel/browser/configure.zcml
collective/analyticspanel/browser/controlpanel.py
collective/analyticspanel/browser/site.py
collective/analyticspanel/browser/site_p4.py
collective/analyticspanel/browser/viewlet.py
collective/analyticspanel/browser/images/analytics.png
collective/analyticspanel/locales/collective.analyticspanel-manual.pot
collective/analyticspanel/locales/collective.analyticspanel.pot
collective/analyticspanel/locales/rebuildPo.sh
collective/analyticspanel/locales/it/LC_MESSAGES/collective.analyticspanel.mo
collective/analyticspanel/locales/it/LC_MESSAGES/collective.analyticspanel.po
collective/analyticspanel/profiles/clean_registry/registry.xml
collective/analyticspanel/profiles/default/browserlayer.xml
collective/analyticspanel/profiles/default/collective.analyticspanel_various.txt
collective/analyticspanel/profiles/default/controlpanel.xml
collective/analyticspanel/profiles/default/metadata.xml
collective/analyticspanel/profiles/default/registry.xml
collective/analyticspanel/profiles/default/rolemap.xml
collective/analyticspanel/profiles/default/skins.xml
collective/analyticspanel/profiles/uninstall/controlpanel.xml
collective/analyticspanel/profiles/uninstall/registry.xml
collective/analyticspanel/profiles/uninstall/skins.xml
collective/analyticspanel/skins/collective.analyticspanel/standard_error_message.py
collective/analyticspanel/tests/__init__.py
collective/analyticspanel/tests/base.py
collective/analyticspanel/tests/test_configuration.py
collective/analyticspanel/tests/test_viewlet.py
