Metadata-Version: 2.1
Name: collective.analyticspanel
Version: 2.0.1
Summary: Add more control over the inclusion of JavaScript analytics code of your Plone site
Home-page: http://plone.org/products/collective.analyticspanel
Author: RedTurtle Technology
Author-email: sviluppoplone@redturtle.it
License: GPL
Keywords: plone analytics plonegov
Classifier: Development Status :: 5 - Production/Stable
Classifier: Framework :: Plone
Classifier: Framework :: Plone :: 5.2
Classifier: Programming Language :: Python
Classifier: Programming Language :: Python :: 3.8
Provides-Extra: test
